Metadata-Version: 1.1
Name: acd2cwl
Version: 0.1.6
Summary: CWL generator for ACD files
Home-page: https://github.com/hmenager/acd2cwl
Author: Hervé Ménager
Author-email: hmenager@pasteur.fr
License: BSD
Download-URL: https://github.com/hmenager/acd2cwl
Keywords: EMBOSS,ACD,Common Workflow Language,CWL
Platform: UNKNOWN
